openvpn_status_parser/__init__.py
openvpn_status_parser/exceptions.py
openvpn_status_parser3-0.0.3.data/scripts/openvpn-status-parser
openvpn_status_parser3-0.0.3.dist-info/METADATA
openvpn_status_parser3-0.0.3.dist-info/WHEEL
openvpn_status_parser3-0.0.3.dist-info/top_level.txt
openvpn_status_parser3-0.0.3.dist-info/RECORD
