Metadata-Version: 2.1
Name: openvpn-status-parser3
Version: 0.0.3
Summary: OpenVPN status parser
Home-page: https://github.com/Niecke/openvpn-status-parser
Author: Daniel Niecke
Author-email: daniel@niecke-it.de
License: BSD
Keywords: openvpn
Platform: UNKNOWN
Classifier: Development Status :: 4 - Beta
Classifier: Intended Audience :: Developers
Classifier: License :: OSI Approved :: MIT License
Classifier: Programming Language :: Python :: 2.6
Classifier: Programming Language :: Python :: 2.7
Classifier: Programming Language :: Python :: 3
Classifier: Programming Language :: Python :: 3.2
Classifier: Programming Language :: Python :: 3.3
Classifier: Programming Language :: Python :: 3.4
Classifier: Programming Language :: Python :: 3.5
Classifier: Programming Language :: Python :: Implementation :: PyPy
Requires-Dist: docopt (>=0.6.2)
Provides-Extra: dev
Requires-Dist: twine ; extra == 'dev'
Requires-Dist: wheel ; extra == 'dev'
